mexcpy/__init__.py
mexcpy/api/__init__.py
mexcpy/api/api_response.py
mexcpy/api/base_api.py
mexcpy/api/endpoints.py
mexcpy/api/market_data.py
mexcpy/api/signature.py
mexcpy/api/spot_account.py
mexcpy/api/wallet_data.py
mexcpy-0.0.1.dist-info/METADATA
mexcpy-0.0.1.dist-info/WHEEL
mexcpy-0.0.1.dist-info/top_level.txt
mexcpy-0.0.1.dist-info/RECORD
