Metadata-Version: 2.1
Name: mexcpy
Version: 0.0.1
Summary: Python3 Mexc API wrapper
Home-page: https://github.com/PurpRabbit/mexcpy
Author: PurpRabbit
Author-email: lysovich28@gmail.com
Classifier: Development Status :: 5 - Production/Stable
Classifier: Intended Audience :: Developers
Classifier: License :: OSI Approved :: MIT License
Classifier: Programming Language :: Python :: 3
Classifier: Programming Language :: Python :: 3.6
Classifier: Programming Language :: Python :: 3.7
Classifier: Programming Language :: Python :: 3.8
Classifier: Programming Language :: Python :: 3.9
Requires-Python: >=3.6
Requires-Dist: requests (==2.28.2)
